{
  "version": "2.0",
  "routeKey": "GET /image/{id}",
  "rawPath": "/image/133601ff1072e5b6eeb8d857dea93f35?size=400",
  "rawQueryString": "",
  "queryStringParameters": {
    "size": "400"
  },
  "requestContext": {
    "accountId": "123456789012",
    "apiId": "api-id",
    "domainName": "id.execute-api.us-east-1.amazonaws.com",
    "domainPrefix": "id",
    "http": {
      "method": "GET",
      "path": "/image/133601ff1072e5b6eeb8d857dea93f35",
      "protocol": "HTTP/1.1",
      "sourceIp": "IP",
      "userAgent": "agent"
    },
    "requestId": "id",
    "routeKey": "GET /content/{id}/{size}",
    "stage": "$default",
    "time": "12/Mar/2020:19:03:58 +0000",
    "timeEpoch": 1583348638390
  },
  "body": "Hello from Lambda",
  "pathParameters": {
    "id": "7588a85cb0cf703e78174bafb24455f8"
  },
  "isBase64Encoded": false,
  "stageVariables": {
    "stageVariable1": "value1",
    "stageVariable2": "value2"
  }
}